gongsf/__init__.py
gongsf/codec.py
gongsf/context.py
gongsf/data.py
gongsf/lib.py
gongsf/types.py
gongsf-0.1.1.dist-info/METADATA
gongsf-0.1.1.dist-info/WHEEL
gongsf-0.1.1.dist-info/RECORD
